holy_bible_api/__init__.py
holy_bible_api/create_bible_api.py
holy_bible_api/py.typed
openapi_client/__init__.py
openapi_client/api_client.py
openapi_client/api_response.py
openapi_client/configuration.py
openapi_client/exceptions.py
openapi_client/py.typed
openapi_client/rest.py
openapi_client/api/__init__.py
openapi_client/api/default_api.py
openapi_client/models/__init__.py
openapi_client/models/audio_bible.py
openapi_client/models/bible.py
openapi_client/models/bible_verse.py
openapi_client/models/get_audio_bibles_res.py
openapi_client/models/get_audio_books_res.py
openapi_client/models/get_audio_chapters_res.py
openapi_client/models/get_bible_books_res.py
openapi_client/models/get_bible_chapters_res.py
openapi_client/models/get_bible_verses_res.py
openapi_client/models/get_bibles_res.py
holy_bible_api_python-7.0.0.dist-info/METADATA
holy_bible_api_python-7.0.0.dist-info/WHEEL
holy_bible_api_python-7.0.0.dist-info/RECORD
