Metadata-Version: 2.4
Name: holy_bible_api_python
Version: 7.0.0
Summary: Add your description here
Requires-Python: >=3.14
Requires-Dist: openapi-client
